cerberus_cli/__init__.py
cerberus_cli/config.py
cerberus_cli/validate.py
cerberus_cli-0.0.3.dist-info/AUTHORS
cerberus_cli-0.0.3.dist-info/METADATA
cerberus_cli-0.0.3.dist-info/WHEEL
cerberus_cli-0.0.3.dist-info/entry_points.txt
cerberus_cli-0.0.3.dist-info/pbr.json
cerberus_cli-0.0.3.dist-info/top_level.txt
cerberus_cli-0.0.3.dist-info/RECORD
