Metadata-Version: 2.1
Name: cerberus-cli
Version: 0.0.3
Summary: Command line interface for the Cerberus schema and data validation tool.
Home-page: https://github.com/moisesguimaraes/cerberus-cli/
Author: Moisés Guimarães de Medeiros
Author-email: contact@moisesguimaraes.com
License: Apache-2.0
Platform: UNKNOWN
Classifier: Development Status :: 4 - Beta
Classifier: Intended Audience :: Developers
Classifier: License :: OSI Approved :: Apache Software License
Classifier: Natural Language :: English
Classifier: Programming Language :: Python
Classifier: Programming Language :: Python :: 3
Classifier: Programming Language :: Python :: 3.6
Classifier: Programming Language :: Python :: 3.7
Classifier: Programming Language :: Python :: 3.8
Classifier: Programming Language :: Python :: 3.9
Requires-Dist: Cerberus (>=1.3.2)
Requires-Dist: PyYAML (>=5.4.1)
Requires-Dist: oslo.config (>=8.5.0)
